kausate/__init__.py
kausate/_base_client.py
kausate/_client.py
kausate/_compat.py
kausate/_constants.py
kausate/_exceptions.py
kausate/_files.py
kausate/_models.py
kausate/_qs.py
kausate/_resource.py
kausate/_response.py
kausate/_streaming.py
kausate/_types.py
kausate/_version.py
kausate/py.typed
kausate/_utils/__init__.py
kausate/_utils/_compat.py
kausate/_utils/_datetime_parse.py
kausate/_utils/_logs.py
kausate/_utils/_proxy.py
kausate/_utils/_reflection.py
kausate/_utils/_resources_proxy.py
kausate/_utils/_streams.py
kausate/_utils/_sync.py
kausate/_utils/_transform.py
kausate/_utils/_typing.py
kausate/_utils/_utils.py
kausate/lib/.keep
kausate/resources/__init__.py
kausate/resources/orders.py
kausate/resources/secrets.py
kausate/resources/webhooks.py
kausate/resources/companies/__init__.py
kausate/resources/companies/companies.py
kausate/resources/companies/documents.py
kausate/resources/companies/products.py
kausate/resources/companies/report.py
kausate/resources/companies/search.py
kausate/types/__init__.py
kausate/types/company_extract_shareholder_graph_params.py
kausate/types/company_extract_ubo_params.py
kausate/types/company_extract_ubo_response.py
kausate/types/company_report.py
kausate/types/currency.py
kausate/types/date_info.py
kausate/types/interest_type.py
kausate/types/legal_form.py
kausate/types/order_list_params.py
kausate/types/order_list_response.py
kausate/types/order_retrieve_params.py
kausate/types/order_retrieve_response.py
kausate/types/percentage_share.py
kausate/types/person.py
kausate/types/product_order_response.py
kausate/types/role.py
kausate/types/secret_create_params.py
kausate/types/secret_delete_params.py
kausate/types/secret_list_params.py
kausate/types/secret_list_response.py
kausate/types/secret_response_public.py
kausate/types/secret_update_params.py
kausate/types/shareholder.py
kausate/types/shareholder_report_data.py
kausate/types/signatory_rules.py
kausate/types/status.py
kausate/types/ultimate_beneficial_owner.py
kausate-0.0.2.dist-info/METADATA
kausate-0.0.2.dist-info/WHEEL
kausate-0.0.2.dist-info/licenses/LICENSE
kausate-0.0.2.dist-info/RECORD
